MANIFEST.in
README.rst
setup.cfg
setup.py
bika/__init__.py
bika.lims.egg-info/PKG-INFO
bika.lims.egg-info/SOURCES.txt
bika.lims.egg-info/dependency_links.txt
bika.lims.egg-info/entry_points.txt
bika.lims.egg-info/namespace_packages.txt
bika.lims.egg-info/not-zip-safe
bika.lims.egg-info/requires.txt
bika.lims.egg-info/top_level.txt
bika/lims/__init__.py
bika/lims/barcode.py
bika/lims/catalog.py
bika/lims/config.py
bika/lims/configure.zcml
bika/lims/fields.py
bika/lims/idserver.py
bika/lims/overrides.zcml
bika/lims/permissions.py
bika/lims/permissions.zcml
bika/lims/profiles.zcml
bika/lims/search.py
bika/lims/search.zcml
bika/lims/setuphandlers.py
bika/lims/testing.py
bika/lims/validators.py
bika/lims/workflow.py
bika/lims/workflow.zcml
bika/lims/adapters/__init__.py
bika/lims/adapters/configure.zcml
bika/lims/adapters/priorityicons.py
bika/lims/adapters/referencewidgetvocabulary.py
bika/lims/adapters/widgetvisibility.py
bika/lims/browser/__init__.py
bika/lims/browser/accreditation.py
bika/lims/browser/analyses.py
bika/lims/browser/analysis.py
bika/lims/browser/analysis.zcml
bika/lims/browser/analysisprofile.py
bika/lims/browser/analysisprofile.zcml
bika/lims/browser/analysisservice.py
bika/lims/browser/analysisservice.zcml
bika/lims/browser/analysisspec.py
bika/lims/browser/analysisspec.zcml
bika/lims/browser/arimports.py
bika/lims/browser/arimports.zcml
bika/lims/browser/artemplate.py
bika/lims/browser/artemplate.zcml
bika/lims/browser/attachment.py
bika/lims/browser/attachment.zcml
bika/lims/browser/batchfolder.py
bika/lims/browser/batchfolder.zcml
bika/lims/browser/bika-frontpage.py
bika/lims/browser/bika-frontpage.zcml
bika/lims/browser/bika_listing.py
bika/lims/browser/bika_listing.zcml
bika/lims/browser/calcs.py
bika/lims/browser/calcs.zcml
bika/lims/browser/clientfolder.py
bika/lims/browser/clientfolder.zcml
bika/lims/browser/configure.zcml
bika/lims/browser/contact.py
bika/lims/browser/contact.zcml
bika/lims/browser/dashboard.py
bika/lims/browser/duplicateanalysis.py
bika/lims/browser/duplicateanalysis.zcml
bika/lims/browser/header_table.py
bika/lims/browser/instrument.py
bika/lims/browser/instrument.zcml
bika/lims/browser/instrumenttype.py
bika/lims/browser/instrumenttype.zcml
bika/lims/browser/invoice.py
