Metadata-Version: 1.1
Name: bika.lims
Version: 3.1.15
Summary: Bika LIMS
Home-page: http://www.bikalims.org
Author: Naralabs
Author-email: info@naralabs.com
License: AGPL
Keywords: lims,bika,opensource
Platform: UNKNOWN
Classifier: Framework :: Plone
Classifier: Programming Language :: Python
Classifier: Development Status :: 5 - Production/Stable
Classifier: Environment :: Web Environment
Classifier: Intended Audience :: Information Technology
Classifier: Intended Audience :: Science/Research
Classifier: License :: OSI Approved :: GNU Affero General Public License v3 or later (AGPLv3+)
